README.md
setup.cfg
setup.py
kek_distributions/Binomialdistribution.py
kek_distributions/Gaussiandistribution.py
kek_distributions/Generaldistribution.py
kek_distributions/__init__.py
kek_distributions.egg-info/PKG-INFO
kek_distributions.egg-info/SOURCES.txt
kek_distributions.egg-info/dependency_links.txt
kek_distributions.egg-info/not-zip-safe
kek_distributions.egg-info/top_level.txt