Metadata-Version: 1.0
Name: kek-distributions
Version: 0.1
Summary: Gaussian and Binomial distributions
Home-page: UNKNOWN
Author: Kristo Krugger
Author-email: kristoelijahkrugger@gmail.com
License: UNKNOWN
Platform: UNKNOWN
